gits/__init__.py
gits/main.py
gits/.system/imports.py
gits/.system/index.py
gits/.system/modules/gitssh.py
gits/.system/sources/clight.json
gits/.system/sources/logo.ico
gits/.system/sources/sshconfig
gits-1.0.5.dist-info/licenses/LICENSE
gits-1.0.5.dist-info/METADATA
gits-1.0.5.dist-info/WHEEL
gits-1.0.5.dist-info/entry_points.txt
gits-1.0.5.dist-info/top_level.txt
gits-1.0.5.dist-info/RECORD
