Metadata-Version: 2.4
Name: gits
Version: 1.0.5
Summary: Gits is a Python command-line application designed to help you to handle multiple GitHub and GitLab repositories on your machine. With using Gits, you can start cloning from and pushing to multiple GitHub and GitLab accounts without any additional configurations - It automatically sets up everything needed to prevent conflicts between your accounts.
Home-page: https://github.com/IG-onGit/Gits
Author: Irakli Gzirishvili
Author-email: gziraklirex@gmail.com
Classifier: Programming Language :: Python :: 3
Classifier: License :: OSI Approved :: MIT License
Classifier: Operating System :: Microsoft :: Windows
License-File: LICENSE
Requires-Dist: clight
Requires-Dist: colored
Dynamic: author
Dynamic: author-email
Dynamic: classifier
Dynamic: description
Dynamic: description-content-type
Dynamic: home-page
Dynamic: license-file
Dynamic: requires-dist
Dynamic: summary
